equinix_metal_t0mk/__init__.py
equinix_metal_t0mk/api_client.py
equinix_metal_t0mk/api_response.py
equinix_metal_t0mk/configuration.py
equinix_metal_t0mk/exceptions.py
equinix_metal_t0mk/py.typed
equinix_metal_t0mk/rest.py
equinix_metal_t0mk/api/__init__.py
equinix_metal_t0mk/api/authentication_api.py
equinix_metal_t0mk/api/batches_api.py
equinix_metal_t0mk/api/bgp_api.py
equinix_metal_t0mk/api/capacity_api.py
equinix_metal_t0mk/api/console_log_details_api.py
equinix_metal_t0mk/api/devices_api.py
equinix_metal_t0mk/api/emails_api.py
equinix_metal_t0mk/api/events_api.py
equinix_metal_t0mk/api/facilities_api.py
equinix_metal_t0mk/api/firmware_sets_api.py
equinix_metal_t0mk/api/hardware_reservations_api.py
equinix_metal_t0mk/api/incidents_api.py
equinix_metal_t0mk/api/interconnections_api.py
equinix_metal_t0mk/api/invitations_api.py
equinix_metal_t0mk/api/invoices_api.py
equinix_metal_t0mk/api/ip_addresses_api.py
equinix_metal_t0mk/api/licenses_api.py
equinix_metal_t0mk/api/memberships_api.py
equinix_metal_t0mk/api/metal_gateways_api.py
equinix_metal_t0mk/api/metros_api.py
equinix_metal_t0mk/api/operating_systems_api.py
equinix_metal_t0mk/api/organizations_api.py
equinix_metal_t0mk/api/otps_api.py
equinix_metal_t0mk/api/password_reset_tokens_api.py
equinix_metal_t0mk/api/payment_methods_api.py
equinix_metal_t0mk/api/plans_api.py
equinix_metal_t0mk/api/ports_api.py
equinix_metal_t0mk/api/projects_api.py
equinix_metal_t0mk/api/self_service_reservations_api.py
equinix_metal_t0mk/api/spot_market_api.py
equinix_metal_t0mk/api/ssh_keys_api.py
equinix_metal_t0mk/api/support_request_api.py
equinix_metal_t0mk/api/transfer_requests_api.py
equinix_metal_t0mk/api/two_factor_auth_api.py
equinix_metal_t0mk/api/usages_api.py
equinix_metal_t0mk/api/user_verification_tokens_api.py
equinix_metal_t0mk/api/userdata_api.py
equinix_metal_t0mk/api/users_api.py
equinix_metal_t0mk/api/vlans_api.py
equinix_metal_t0mk/api/vrfs_api.py
equinix_metal_t0mk/models/__init__.py
equinix_metal_t0mk-1.0.0.dist-info/METADATA
equinix_metal_t0mk-1.0.0.dist-info/WHEEL
equinix_metal_t0mk-1.0.0.dist-info/top_level.txt
equinix_metal_t0mk-1.0.0.dist-info/RECORD
